airpg/__init__.py
airpg/article_mining.py
airpg/entrez_interaction.py
airpg/ir_operations.py
airpg/parse_pubmed.py
airpg/self_blasting.py
airpg/table_io.py
airpg/scripts/__init__.py
airpg/scripts/airpg_analyze.py
airpg/scripts/airpg_confirm.py
airpg/scripts/airpg_identify.py
airpg/scripts/airpg_update_blocklist.py
airpg-1.1.4.data/scripts/airpg_analyze.py
airpg-1.1.4.data/scripts/airpg_confirm.py
airpg-1.1.4.data/scripts/airpg_identify.py
airpg-1.1.4.data/scripts/airpg_update_blocklist.py
airpg-1.1.4.dist-info/AUTHORS
airpg-1.1.4.dist-info/LICENSE
airpg-1.1.4.dist-info/METADATA
airpg-1.1.4.dist-info/WHEEL
airpg-1.1.4.dist-info/top_level.txt
airpg-1.1.4.dist-info/RECORD
