Metadata-Version: 2.1
Name: airpg
Version: 1.1.4
Summary: A package to automatically access the inverted repeats of archived plastid genomes
Home-page: https://github.com/michaelgruenstaeudl/airpg
Author: Michael Gruenstaeudl, Tilman Mehl
Author-email: m.gruenstaeudl@fu-berlin.de, tilmanmehl@zedat.fu-berlin.de
License: GPLv3
Keywords: plastid genomes,inverted repeats,NCBI Nucleotide
Platform: UNKNOWN
Classifier: Development Status :: 4 - Beta
Classifier: License :: OSI Approved :: GNU General Public License v3 (GPLv3)
Classifier: Programming Language :: Python :: 3
Classifier: Operating System :: POSIX
Classifier: Intended Audience :: Science/Research
Classifier: Topic :: Scientific/Engineering :: Bio-Informatics
Requires-Python: >=3.6
Requires-Dist: biopython
Requires-Dist: ete3
Requires-Dist: entrezpy
Requires-Dist: pandas
Requires-Dist: fuzzywuzzy
Requires-Dist: coloredlogs
Requires-Dist: python-Levenshtein
